<annotation>
	<folder>good_apple2</folder>
	<filename>freshApple (473).png</filename>
	<path>D:\TensorFlow FYP\Fruit-Spoilage-Detection-Dataset\dataset\complete\good_apple\good_apple2\freshApple (473).png</path>
	<source>
		<database>Unknown</database>
	</source>
	<size>
		<width>480</width>
		<height>322</height>
		<depth>3</depth>
	</size>
	<segmented>0</segmented>
	<object>
		<name>fresh</name>
		<pose>Unspecified</pose>
		<truncated>0</truncated>
		<difficult>0</difficult>
		<bndbox>
			<xmin>135</xmin>
			<ymin>72</ymin>
			<xmax>241</xmax>
			<ymax>176</ymax>
		</bndbox>
	</object>
	<object>
		<name>fresh</name>
		<pose>Unspecified</pose>
		<truncated>0</truncated>
		<difficult>0</difficult>
		<bndbox>
			<xmin>99</xmin>
			<ymin>153</ymin>
			<xmax>216</xmax>
			<ymax>261</ymax>
		</bndbox>
	</object>
	<object>
		<name>fresh</name>
		<pose>Unspecified</pose>
		<truncated>0</truncated>
		<difficult>0</difficult>
		<bndbox>
			<xmin>186</xmin>
			<ymin>198</ymin>
			<xmax>310</xmax>
			<ymax>312</ymax>
		</bndbox>
	</object>
	<object>
		<name>fresh</name>
		<pose>Unspecified</pose>
		<truncated>0</truncated>
		<difficult>0</difficult>
		<bndbox>
			<xmin>231</xmin>
			<ymin>108</ymin>
			<xmax>331</xmax>
			<ymax>214</ymax>
		</bndbox>
	</object>
	<object>
		<name>fresh</name>
		<pose>Unspecified</pose>
		<truncated>0</truncated>
		<difficult>0</difficult>
		<bndbox>
			<xmin>215</xmin>
			<ymin>15</ymin>
			<xmax>323</xmax>
			<ymax>114</ymax>
		</bndbox>
	</object>
	<object>
		<name>fresh</name>
		<pose>Unspecified</pose>
		<truncated>0</truncated>
		<difficult>0</difficult>
		<bndbox>
			<xmin>311</xmin>
			<ymin>32</ymin>
			<xmax>434</xmax>
			<ymax>150</ymax>
		</bndbox>
	</object>
	<object>
		<name>fresh</name>
		<pose>Unspecified</pose>
		<truncated>0</truncated>
		<difficult>0</difficult>
		<bndbox>
			<xmin>316</xmin>
			<ymin>139</ymin>
			<xmax>437</xmax>
			<ymax>245</ymax>
		</bndbox>
	</object>
</annotation>
