<annotation>
	<folder>good_banana1</folder>
	<filename>IMG20200730132039.jpg</filename>
	<path>D:\TensorFlow FYP\Fruit-Spoilage-Detection-Dataset\dataset\complete\good_banana\good_banana1\IMG20200730132039.jpg</path>
	<source>
		<database>Unknown</database>
	</source>
	<size>
		<width>192</width>
		<height>256</height>
		<depth>3</depth>
	</size>
	<segmented>0</segmented>
	<object>
		<name>fresh</name>
		<pose>Unspecified</pose>
		<truncated>0</truncated>
		<difficult>0</difficult>
		<bndbox>
			<xmin>97</xmin>
			<ymin>70</ymin>
			<xmax>165</xmax>
			<ymax>198</ymax>
		</bndbox>
	</object>
	<object>
		<name>fresh</name>
		<pose>Unspecified</pose>
		<truncated>0</truncated>
		<difficult>0</difficult>
		<bndbox>
			<xmin>63</xmin>
			<ymin>71</ymin>
			<xmax>113</xmax>
			<ymax>197</ymax>
		</bndbox>
	</object>
	<object>
		<name>fresh</name>
		<pose>Unspecified</pose>
		<truncated>0</truncated>
		<difficult>0</difficult>
		<bndbox>
			<xmin>29</xmin>
			<ymin>62</ymin>
			<xmax>89</xmax>
			<ymax>206</ymax>
		</bndbox>
	</object>
</annotation>
