<annotation>
	<folder>bad_orange1</folder>
	<filename>IMG20200728140729.jpg</filename>
	<path>D:\TensorFlow FYP\Fruit-Spoilage-Detection-Dataset\dataset\complete\bad_orange\bad_orange1\IMG20200728140729.jpg</path>
	<source>
		<database>Unknown</database>
	</source>
	<size>
		<width>256</width>
		<height>192</height>
		<depth>3</depth>
	</size>
	<segmented>0</segmented>
	<object>
		<name>rotten</name>
		<pose>Unspecified</pose>
		<truncated>0</truncated>
		<difficult>0</difficult>
		<bndbox>
			<xmin>76</xmin>
			<ymin>4</ymin>
			<xmax>142</xmax>
			<ymax>68</ymax>
		</bndbox>
	</object>
	<object>
		<name>rotten</name>
		<pose>Unspecified</pose>
		<truncated>0</truncated>
		<difficult>0</difficult>
		<bndbox>
			<xmin>80</xmin>
			<ymin>70</ymin>
			<xmax>143</xmax>
			<ymax>123</ymax>
		</bndbox>
	</object>
	<object>
		<name>rotten</name>
		<pose>Unspecified</pose>
		<truncated>0</truncated>
		<difficult>0</difficult>
		<bndbox>
			<xmin>139</xmin>
			<ymin>49</ymin>
			<xmax>196</xmax>
			<ymax>106</ymax>
		</bndbox>
	</object>
	<object>
		<name>rotten</name>
		<pose>Unspecified</pose>
		<truncated>0</truncated>
		<difficult>0</difficult>
		<bndbox>
			<xmin>158</xmin>
			<ymin>105</ymin>
			<xmax>219</xmax>
			<ymax>178</ymax>
		</bndbox>
	</object>
	<object>
		<name>rotten</name>
		<pose>Unspecified</pose>
		<truncated>0</truncated>
		<difficult>0</difficult>
		<bndbox>
			<xmin>101</xmin>
			<ymin>119</ymin>
			<xmax>164</xmax>
			<ymax>187</ymax>
		</bndbox>
	</object>
</annotation>
