<annotation>
	<folder>bad_banana1</folder>
	<filename>IMG_20190910_175159.jpg</filename>
	<path>D:\TensorFlow FYP\Fruit-Spoilage-Detection-Dataset\dataset\complete\bad_banana\bad_banana1\IMG_20190910_175159.jpg</path>
	<source>
		<database>Unknown</database>
	</source>
	<size>
		<width>256</width>
		<height>256</height>
		<depth>3</depth>
	</size>
	<segmented>0</segmented>
	<object>
		<name>rotten</name>
		<pose>Unspecified</pose>
		<truncated>1</truncated>
		<difficult>0</difficult>
		<bndbox>
			<xmin>54</xmin>
			<ymin>54</ymin>
			<xmax>256</xmax>
			<ymax>234</ymax>
		</bndbox>
	</object>
</annotation>
