<annotation>
	<folder>bad_apple1</folder>
	<filename>IMG_20190910_171731.jpg</filename>
	<path>D:\TensorFlow FYP\Fruit-Spoilage-Detection-Dataset\dataset\complete\bad_apple\bad_apple1\IMG_20190910_171731.jpg</path>
	<source>
		<database>Unknown</database>
	</source>
	<size>
		<width>256</width>
		<height>256</height>
		<depth>3</depth>
	</size>
	<segmented>0</segmented>
	<object>
		<name>rotten</name>
		<pose>Unspecified</pose>
		<truncated>0</truncated>
		<difficult>0</difficult>
		<bndbox>
			<xmin>74</xmin>
			<ymin>54</ymin>
			<xmax>214</xmax>
			<ymax>182</ymax>
		</bndbox>
	</object>
</annotation>
