<annotation>
	<folder>good_orange3</folder>
	<filename>rotated_by_15_Screen Shot 2018-06-13 at 12.18.07 AM.png</filename>
	<path>D:\TensorFlow FYP\Fruit-Spoilage-Detection-Dataset\dataset\complete\good_orange\good_orange3\rotated_by_15_Screen Shot 2018-06-13 at 12.18.07 AM.png</path>
	<source>
		<database>Unknown</database>
	</source>
	<size>
		<width>312</width>
		<height>290</height>
		<depth>3</depth>
	</size>
	<segmented>0</segmented>
	<object>
		<name>fresh</name>
		<pose>Unspecified</pose>
		<truncated>0</truncated>
		<difficult>0</difficult>
		<bndbox>
			<xmin>29</xmin>
			<ymin>24</ymin>
			<xmax>285</xmax>
			<ymax>284</ymax>
		</bndbox>
	</object>
</annotation>
