<annotation>
	<folder />
	<filename>saltandpepper_Screen-Shot-2018-06-12-at-11-38-19-PM_png.rf.104e7375a8cad00b66bef35d44d4190c.jpg</filename>
	<path>saltandpepper_Screen-Shot-2018-06-12-at-11-38-19-PM_png.rf.104e7375a8cad00b66bef35d44d4190c.jpg</path>
	<source>
		<database>roboflow.com</database>
	</source>
	<size>
		<width>416</width>
		<height>416</height>
		<depth>3</depth>
	</size>
	<segmented>0</segmented>
	<object>
		<name>rotten</name>
		<pose>Unspecified</pose>
		<truncated>0</truncated>
		<difficult>0</difficult>
		<bndbox>
			<xmin>3</xmin>
			<xmax>389</xmax>
			<ymin>3</ymin>
			<ymax>412</ymax>
		</bndbox>
	</object>
</annotation>