<annotation>
	<folder />
	<filename>V006_80_0_00_02_01_25_0_c35_20201026_0168_S01_1_jpg.rf.ccda71b47d6dac0cc10c77b0ff6abbd3.jpg</filename>
	<path>V006_80_0_00_02_01_25_0_c35_20201026_0168_S01_1_jpg.rf.ccda71b47d6dac0cc10c77b0ff6abbd3.jpg</path>
	<source>
		<database>roboflow.com</database>
	</source>
	<size>
		<width>640</width>
		<height>640</height>
		<depth>3</depth>
	</size>
	<segmented>0</segmented>
	<object>
		<name>fresh</name>
		<pose>Unspecified</pose>
		<truncated>0</truncated>
		<difficult>0</difficult>
		<bndbox>
			<xmin>120</xmin>
			<xmax>550</xmax>
			<ymin>114</ymin>
			<ymax>482</ymax>
		</bndbox>
	</object>
</annotation>