<annotation>
	<folder />
	<filename>V006_80_0_00_02_01_25_0_a01_20201028_0011_S01_jpg.rf.e8f9356b6a52bb0ec0ab9afff8250b5e.jpg</filename>
	<path>V006_80_0_00_02_01_25_0_a01_20201028_0011_S01_jpg.rf.e8f9356b6a52bb0ec0ab9afff8250b5e.jpg</path>
	<source>
		<database>roboflow.com</database>
	</source>
	<size>
		<width>640</width>
		<height>640</height>
		<depth>3</depth>
	</size>
	<segmented>0</segmented>
	<object>
		<name>fresh</name>
		<pose>Unspecified</pose>
		<truncated>0</truncated>
		<difficult>0</difficult>
		<bndbox>
			<xmin>176</xmin>
			<xmax>182</xmax>
			<ymin>207</ymin>
			<ymax>224</ymax>
		</bndbox>
	</object>
	<object>
		<name>fresh</name>
		<pose>Unspecified</pose>
		<truncated>0</truncated>
		<difficult>0</difficult>
		<bndbox>
			<xmin>139</xmin>
			<xmax>595</xmax>
			<ymin>207</ymin>
			<ymax>506</ymax>
		</bndbox>
	</object>
</annotation>