<annotation>
	<folder />
	<filename>V006_80_0_00_02_01_25_0_c34_20201026_0088_S01_1_JPG.rf.79951d6f2b2aaa34d4a71e0cdb256d07.jpg</filename>
	<path>V006_80_0_00_02_01_25_0_c34_20201026_0088_S01_1_JPG.rf.79951d6f2b2aaa34d4a71e0cdb256d07.jpg</path>
	<source>
		<database>roboflow.com</database>
	</source>
	<size>
		<width>640</width>
		<height>640</height>
		<depth>3</depth>
	</size>
	<segmented>0</segmented>
	<object>
		<name>fresh</name>
		<pose>Unspecified</pose>
		<truncated>0</truncated>
		<difficult>0</difficult>
		<bndbox>
			<xmin>207</xmin>
			<xmax>459</xmax>
			<ymin>197</ymin>
			<ymax>524</ymax>
		</bndbox>
	</object>
</annotation>