<annotation>
	<folder />
	<filename>V006_80_0_00_02_01_25_0_b09_20201014_0228_S01_1_jpg.rf.a031002dd20887e191651fb0f1c068fc.jpg</filename>
	<path>V006_80_0_00_02_01_25_0_b09_20201014_0228_S01_1_jpg.rf.a031002dd20887e191651fb0f1c068fc.jpg</path>
	<source>
		<database>roboflow.com</database>
	</source>
	<size>
		<width>640</width>
		<height>640</height>
		<depth>3</depth>
	</size>
	<segmented>0</segmented>
	<object>
		<name>fresh</name>
		<pose>Unspecified</pose>
		<truncated>0</truncated>
		<difficult>0</difficult>
		<bndbox>
			<xmin>156</xmin>
			<xmax>404</xmax>
			<ymin>134</ymin>
			<ymax>590</ymax>
		</bndbox>
	</object>
	<object>
		<name>fresh</name>
		<pose>Unspecified</pose>
		<truncated>0</truncated>
		<difficult>0</difficult>
		<bndbox>
			<xmin>61</xmin>
			<xmax>227</xmax>
			<ymin>432</ymin>
			<ymax>641</ymax>
		</bndbox>
	</object>
</annotation>