<annotation>
	<folder />
	<filename>V006_80_0_00_02_01_25_0_b08_20201026_0000_S01_jpg.rf.e7a8cb594f7b3873a97196371bc0d3ea.jpg</filename>
	<path>V006_80_0_00_02_01_25_0_b08_20201026_0000_S01_jpg.rf.e7a8cb594f7b3873a97196371bc0d3ea.jpg</path>
	<source>
		<database>roboflow.com</database>
	</source>
	<size>
		<width>640</width>
		<height>640</height>
		<depth>3</depth>
	</size>
	<segmented>0</segmented>
	<object>
		<name>fresh</name>
		<pose>Unspecified</pose>
		<truncated>0</truncated>
		<difficult>0</difficult>
		<bndbox>
			<xmin>153</xmin>
			<xmax>470</xmax>
			<ymin>182</ymin>
			<ymax>415</ymax>
		</bndbox>
	</object>
</annotation>