<annotation>
	<folder />
	<filename>V006_80_1_07_02_01_23_2_4498w_20201021_123_JPG.rf.d10daefde9218aa54ab02a78d37a30ef.jpg</filename>
	<path>V006_80_1_07_02_01_23_2_4498w_20201021_123_JPG.rf.d10daefde9218aa54ab02a78d37a30ef.jpg</path>
	<source>
		<database>roboflow.com</database>
	</source>
	<size>
		<width>640</width>
		<height>640</height>
		<depth>3</depth>
	</size>
	<segmented>0</segmented>
	<object>
		<name>rotten</name>
		<pose>Unspecified</pose>
		<truncated>0</truncated>
		<difficult>0</difficult>
		<bndbox>
			<xmin>116</xmin>
			<xmax>570</xmax>
			<ymin>37</ymin>
			<ymax>613</ymax>
		</bndbox>
	</object>
</annotation>